datacenter_datasdk_bin/__init__.py
datacenter_datasdk_bin/taos_api.py
datacenter_datasdk_bin/verify.py
datacenter_datasdk_bin-0.1.5.dist-info/LICENSE.txt
datacenter_datasdk_bin-0.1.5.dist-info/METADATA
datacenter_datasdk_bin-0.1.5.dist-info/WHEEL
datacenter_datasdk_bin-0.1.5.dist-info/top_level.txt
datacenter_datasdk_bin-0.1.5.dist-info/zip-safe
datacenter_datasdk_bin-0.1.5.dist-info/RECORD
