Metadata-Version: 2.1
Name: datacenter-datasdk-bin
Version: 0.1.5
Summary: datacenter_datasdk_bin
Home-page: UNKNOWN
Author: Wang Sheng
Author-email: jayed008@163.com
License: MIT
Platform: UNKNOWN
Classifier: Intended Audience :: Developers
Classifier: License :: OSI Approved :: MIT License
Classifier: Operating System :: MacOS
Classifier: Operating System :: Microsoft
Classifier: Operating System :: POSIX
Classifier: Operating System :: Unix
Classifier: Topic :: Software Development :: Libraries :: Python Modules
Classifier: Programming Language :: Python :: 3.7
Classifier: Programming Language :: Python :: 3.8
License-File: LICENSE.txt
Requires-Dist: pandas (>=0.25.3)
Requires-Dist: numpy (>=1.18.4)
Requires-Dist: taos (==2.0.11)
